pystitia/__init__.py
pystitia/pystitia.py
pystitia-1.4.post1.dist-info/licenses/LICENSE
pystitia-1.4.post1.dist-info/METADATA
pystitia-1.4.post1.dist-info/WHEEL
pystitia-1.4.post1.dist-info/top_level.txt
pystitia-1.4.post1.dist-info/RECORD
