Metadata-Version: 2.4
Name: pystitia
Version: 1.4.post1
Summary: Design by Contract for Python
Author-email: Ashwin Panchapakesan <ashwin.panchapakesan@gmail.com>
License-Expression: Apache-2.0
Project-URL: Homepage, https://github.com/inspectorG4dget/pystitia
Project-URL: Issues, https://github.com/inspectorG4dget/pystitia/issues
Classifier: Programming Language :: Python :: 3
Classifier: Operating System :: OS Independent
Requires-Python: >=3.6
License-File: LICENSE
Dynamic: license-file
